setup.py
poliglo/__init__.py
poliglo/inputs.py
poliglo/outputs.py
poliglo/preparation.py
poliglo/runner.py
poliglo/start.py
poliglo/status.py
poliglo/utils.py
poliglo/variables.py
poliglo.egg-info/PKG-INFO
poliglo.egg-info/SOURCES.txt
poliglo.egg-info/dependency_links.txt
poliglo.egg-info/entry_points.txt
poliglo.egg-info/not-zip-safe
poliglo.egg-info/pbr.json
poliglo.egg-info/requires.txt
poliglo.egg-info/top_level.txt