Metadata-Version: 1.0
Name: poliglo
Version: 0.1.0
Summary: Python client for poliglo (https://github.com/dperezrada/poliglo)
Home-page: https://github.com/dperezrada/poliglo-py
Author: Daniel Pérez Rada
Author-email: dperezrada@gmail.com
License: MIT
Platform: UNKNOWN
